<?xml version="1.0" encoding="UTF-8"?>
<settings xmlns="http://maven.apache.org/SETTINGS/1.0.0"
	xmlns:xsi="http://www.w3.org/2001/XMLSchema-instance"
	xsi:schemaLocation="http://maven.apache.org/SETTINGS/1.0.0
                      http://maven.apache.org/xsd/settings-1.0.0.xsd">
	<servers>
		<server>
			<id>mavenlocal</id>
			<username>u</username>
			<password>p</password>
		</server>
	</servers>

	<profiles>
		<profile>
			<id>useExternalRepositories</id>
			<activation>
				<activeByDefault>true</activeByDefault>
			</activation>
			<repositories>
				<repository>
					<id>jboss-public-repository-group</id>
					<name>JBoss Public Maven Repository Group</name>
					<url>https://repository.jboss.org/nexus/content/groups/public-jboss/</url>
					<layout>default</layout>
					<releases>
						<enabled>true</enabled>
						<updatePolicy>daily</updatePolicy>
					</releases>
					<snapshots>
						<enabled>true</enabled>
						<updatePolicy>daily</updatePolicy>
					</snapshots>
				</repository>
				<repository>
					<id>vaadin-snapshots</id>
					<url>http://oss.sonatype.org/content/repositories/vaadin-snapshots/</url>
					<releases>
						<updatePolicy>daily</updatePolicy>
					</releases>
					<snapshots>
						<enabled>true</enabled>
						<updatePolicy>daily</updatePolicy>
					</snapshots>
				</repository>
				<repository>
					<id>vaadin-addons</id>
					<url>http://maven.vaadin.com/vaadin-addons</url>
					<releases>
						<enabled>true</enabled>
						<updatePolicy>daily</updatePolicy>
					</releases>
					<snapshots>
						<enabled>true</enabled>
						<updatePolicy>daily</updatePolicy>
					</snapshots>
				</repository>
				<repository>
					<id>eclipselink</id>
					<name>EclipseLink</name>
					<url>http://download.eclipse.org/rt/eclipselink/maven.repo</url>
					<layout>default</layout>
					<releases>
						<enabled>true</enabled>
						<updatePolicy>daily</updatePolicy>
					</releases>
					<snapshots>
						<enabled>true</enabled>
						<updatePolicy>daily</updatePolicy>
					</snapshots>
				</repository>
				<repository>
					<id>Codehaus Snapshots</id>
					<url>http://nexus.codehaus.org/snapshots/</url>
					<snapshots>
						<enabled>true</enabled>
					</snapshots>
					<releases>
						<enabled>false</enabled>
					</releases>
				</repository>
			</repositories>
			<pluginRepositories>
				<pluginRepository>
					<id>Codehaus Snapshots</id>
					<url>http://nexus.codehaus.org/snapshots/</url>
					<snapshots>
						<enabled>true</enabled>
					</snapshots>
					<releases>
						<enabled>true</enabled>  <!-- Workaround for MNG-2974, see note below -->
					</releases>
				</pluginRepository>
			</pluginRepositories>
		</profile>

		<profile>
			<id>artifactory</id>
			<repositories>
				<repository>
					<releases>
						<enabled>true</enabled>
						<updatePolicy>daily</updatePolicy>
					</releases>
					<snapshots>
						<enabled>false</enabled>
						<updatePolicy>daily</updatePolicy>
					</snapshots>
					<id>central</id>
					<name>libs-releases</name>
					<url>http://172.206.0.80:8080/artifactory/libs-releases</url>
				</repository>
				<repository>
					<releases>
						<enabled>true</enabled>
						<updatePolicy>daily</updatePolicy>
					</releases>
					<snapshots>
						<enabled>true</enabled>
						<updatePolicy>daily</updatePolicy>
					</snapshots>
					<id>snapshots</id>
					<name>libs-snapshots</name>
					<url>http://172.206.0.80:8080/artifactory/libs-snapshots</url>
				</repository>
			</repositories>
			<pluginRepositories>
				<pluginRepository>
					<snapshots>
						<enabled>false</enabled>
					</snapshots>
					<id>central</id>
					<name>plugins-releases</name>
					<url>http://172.206.0.80:8080/artifactory/plugins-releases</url>
				</pluginRepository>
				<pluginRepository>
					<snapshots />
					<id>snapshots</id>
					<name>plugins-snapshots</name>
					<url>http://172.206.0.80:8080/artifactory/plugins-snapshots</url>
				</pluginRepository>
			</pluginRepositories>
		</profile>

		<profile>
			<id>forceUpdate</id>
			<repositories>
				<repository>
					<releases>
						<enabled>true</enabled>
						<updatePolicy>always</updatePolicy>
					</releases>
					<snapshots>
						<enabled>false</enabled>
						<updatePolicy>always</updatePolicy>
					</snapshots>
					<id>central</id>
					<name>libs-releases</name>
					<url>http://172.206.0.80:8080/artifactory/libs-releases</url>
				</repository>
				<repository>
					<releases>
						<enabled>false</enabled>
						<updatePolicy>always</updatePolicy>
					</releases>
					<snapshots>
						<enabled>true</enabled>
						<updatePolicy>always</updatePolicy>
					</snapshots>
					<id>snapshots</id>
					<name>libs-snapshots</name>
					<url>http://172.206.0.80:8080/artifactory/libs-snapshots</url>
				</repository>
			</repositories>
			<pluginRepositories>
				<pluginRepository>
					<releases>
						<enabled>true</enabled>
						<updatePolicy>always</updatePolicy>
					</releases>
					<snapshots>
						<enabled>false</enabled>
						<updatePolicy>always</updatePolicy>
					</snapshots>
					<id>central</id>
					<name>plugins-releases</name>
					<url>http://172.206.0.80:8080/artifactory/plugins-releases</url>
				</pluginRepository>
				<pluginRepository>
					<releases>
						<enabled>false</enabled>
						<updatePolicy>always</updatePolicy>
					</releases>
					<snapshots>
						<enabled>true</enabled>
						<updatePolicy>always</updatePolicy>
					</snapshots>
					<id>snapshots</id>
					<name>plugins-snapshots</name>
					<url>http://172.206.0.80:8080/artifactory/plugins-snapshots</url>
				</pluginRepository>
			</pluginRepositories>
		</profile>
	</profiles>

	<activeProfiles>
		<activeProfile>useExternalRepositories</activeProfile>
		<activeProfile>dev</activeProfile>
	</activeProfiles>

</settings>
